Metadata-Version: 2.1
Name: spectra2rgb
Version: 1.0.0
Summary: Converts multi-spectrum cube to RGB image
Home-page: https://github.com/bawaji94/spectra2rgb
Author: Shabbir Nuruddin Bawaji
Author-email: bawaji94@gmail.com
License-File: LICENSE
